chapps/__init__.py
chapps/_version.py
chapps/actions.py
chapps/adapter.py
chapps/config.py
chapps/logging.py
chapps/outbound.py
chapps/policy.py
chapps/signals.py
chapps/spf_policy.py
chapps/switchboard.py
chapps/util.py
chapps-0.3.2.data/data/chapps/INSTALLATION.md
chapps-0.3.2.data/data/chapps/README.md
chapps-0.3.2.data/data/chapps/install/chapps_greylisting.service
chapps-0.3.2.data/data/chapps/install/chapps_multi.service
chapps-0.3.2.data/data/chapps/install/chapps_oqp.service
chapps-0.3.2.data/data/chapps/postfix/greylisting/main.cf
chapps-0.3.2.data/data/chapps/postfix/greylisting/master.cf
chapps-0.3.2.data/data/chapps/postfix/null_filter/main.cf
chapps-0.3.2.data/data/chapps/postfix/null_filter/master.cf
chapps-0.3.2.data/data/chapps/postfix/outbound_quota/main.cf
chapps-0.3.2.data/data/chapps/postfix/outbound_quota/master.cf
chapps-0.3.2.data/scripts/chapps_database_init.py
chapps-0.3.2.data/scripts/chapps_greylisting.py
chapps-0.3.2.data/scripts/chapps_outbound_multi.py
chapps-0.3.2.data/scripts/chapps_outbound_quota.py
chapps-0.3.2.data/scripts/null_filter.py
chapps-0.3.2.dist-info/LICENSE.txt
chapps-0.3.2.dist-info/METADATA
chapps-0.3.2.dist-info/WHEEL
chapps-0.3.2.dist-info/top_level.txt
chapps-0.3.2.dist-info/RECORD
