Metadata-Version: 2.1
Name: chapps
Version: 0.3.2
Summary: Caching, Highly-Available Postfix Policy Service
Home-page: https://gitlab.int.easydns.net/ccullen/chapps
Download-URL: https://github.com/easydns/chapps/tree/main/dist/chapps-0.3.2.tar.gz
Author: Caleb S. Cullen
Author-email: ccullen@easydns.com
License: MIT
Keywords: Postfix,Policy,Daemon
Platform: UNKNOWN
Classifier: Development Status :: 3 - Alpha
Classifier: Environment :: No Input/Output (Daemon)
Classifier: Intended Audience :: System Administrators
Classifier: Operating System :: POSIX :: Linux
Classifier: Topic :: Communications :: Email :: Filters
Classifier: License :: OSI Approved :: MIT License
Classifier: Programming Language :: Python :: 3.8
Classifier: Programming Language :: Python :: 3.9
Classifier: Programming Language :: Python :: 3.10
Requires-Python: >=3.8
License-File: LICENSE.txt
Requires-Dist: redis
Requires-Dist: expiring-dict
Requires-Dist: dnspython
Requires-Dist: mariadb
Requires-Dist: pyspf
Requires-Dist: python-pidfile
